textcode_pdf2text/__init__.py
textcode_pdf2text/bin/pdftotext
textcode_pdf2text/licenses/ANNOUNCE
textcode_pdf2text/licenses/CHANGES
textcode_pdf2text/licenses/COPYING
textcode_pdf2text/licenses/COPYING3
textcode_pdf2text/licenses/INSTALL
textcode_pdf2text/licenses/README
textcode_pdf2text/licenses/pdftotext.1
textcode_pdf2text-4.3.210217.dist-info/METADATA
textcode_pdf2text-4.3.210217.dist-info/README.rst
textcode_pdf2text-4.3.210217.dist-info/WHEEL
textcode_pdf2text-4.3.210217.dist-info/apache-2.0.LICENSE
textcode_pdf2text-4.3.210217.dist-info/entry_points.txt
textcode_pdf2text-4.3.210217.dist-info/gpl-2.0.LICENSE
textcode_pdf2text-4.3.210217.dist-info/gpl-3.0.LICENSE
textcode_pdf2text-4.3.210217.dist-info/pdf2text.ABOUT
textcode_pdf2text-4.3.210217.dist-info/pdf2text.NOTICE
textcode_pdf2text-4.3.210217.dist-info/textcode-pdf2text.ABOUT
textcode_pdf2text-4.3.210217.dist-info/top_level.txt
textcode_pdf2text-4.3.210217.dist-info/RECORD
