Metadata-Version: 2.1
Name: textcode-pdf2text
Version: 4.3.210217
Summary: A ScanCode path provider plugin to provide a prebuilt native libmagic binary and database.
Home-page: https://github.com/nexB/scancode-plugins
Author: nexB
Author-email: info@aboutcode.org
License: apache-2.0 AND (gpl-2.0 OR gpl-3.0)
Keywords: open source,textcode,scancode,pdf,pdf2text,xpdf
Platform: UNKNOWN
Classifier: Development Status :: 5 - Production/Stable
Classifier: Intended Audience :: Developers
Classifier: Topic :: Utilities
